Metadata-Version: 2.1
Name: spoclify
Version: 1.3.6
Summary: A CLI to interface with Spotify
Home-page: http://github.com/Naapperas/Spoclify
Author: Nuno Pereira
Author-email: nunoafonso2002@gmail.com
License: MIT
Platform: UNKNOWN
